setup.py
stream_anywhere/__init__.py
stream_anywhere.egg-info/PKG-INFO
stream_anywhere.egg-info/SOURCES.txt
stream_anywhere.egg-info/dependency_links.txt
stream_anywhere.egg-info/not-zip-safe
stream_anywhere.egg-info/top_level.txt