Metadata-Version: 1.1
Name: stream-anywhere
Version: 0.1.0a0
Summary: Package description
